cmp3/__init__.py
cmp3/core/__init__.py
cmp3/tests/__init__.py
cmp3/tests/test_1984.py
cmp3-0.6.2.dist-info/licenses/LICENSE.txt
cmp3-0.6.2.dist-info/METADATA
cmp3-0.6.2.dist-info/WHEEL
cmp3-0.6.2.dist-info/top_level.txt
cmp3-0.6.2.dist-info/RECORD
