Metadata-Version: 2.4
Name: cmp3
Version: 0.6.2
Summary: This project updates the concept of __cmp__ for python3.
Author-email: Johannes <johannes.programming@gmail.com>
License: The MIT License (MIT)
Project-URL: Download, https://pypi.org/project/cmp3/#files
Project-URL: Index, https://pypi.org/project/cmp3/
Project-URL: Source, https://github.com/johannes-programming/cmp3/
Project-URL: Website, https://cmp3.johannes-programming.online/
Classifier: Development Status :: 3 - Alpha
Classifier: License :: OSI Approved :: MIT License
Classifier: Natural Language :: English
Classifier: Operating System :: OS Independent
Classifier: Programming Language :: Python
Classifier: Programming Language :: Python :: 3
Classifier: Programming Language :: Python :: 3 :: Only
Classifier: Typing :: Typed
Requires-Python: >=3.11
License-File: LICENSE.txt
Requires-Dist: setdoc<2,>=1.2.6
Dynamic: license-file
